{
  "updated": "2026/07/06",
  "updated_ts": "2026-07-06T19:10:15.069666+08:00",
  "vusion": {
    "current": 140.5,
    "prev": 137.8,
    "chg": 1.96,
    "currency": "EUR",
    "h52": 278.0,
    "l52": 108.5,
    "target": 223.13,
    "rating": "強力買入",
    "ytd": -44.7,
    "is_live": true
  },
  "solum": {
    "current": 15350.0,
    "prev": 15850.0,
    "chg": -3.15,
    "currency": "KRW",
    "h52": 20750,
    "l52": 13870,
    "target": 22000,
    "rating": "強力買入",
    "ytd": -13.1,
    "is_live": true
  },
  "eink": {
    "current": 205.5,
    "prev": 204.0,
    "chg": 0.74,
    "currency": "TWD",
    "h52": 312.0,
    "l52": 164.5,
    "target": 266.83,
    "rating": "買入",
    "ytd": -41.5,
    "is_live": true
  },
  "pricer": {
    "current": 3.29,
    "prev": 3.255,
    "chg": 1.08,
    "currency": "SEK",
    "h52": 9.92,
    "l52": 2.91,
    "target": 7.13,
    "rating": "持有",
    "ytd": -65.1,
    "is_live": true
  }
}