{
  "updated": "2026/04/22",
  "updated_ts": "2026-04-22T02:39:33.771146+08:00",
  "vusion": {
    "current": 118.8,
    "prev": 119.6,
    "chg": -0.67,
    "currency": "EUR",
    "h52": 278.0,
    "l52": 108.5,
    "target": 223.13,
    "rating": "強力買入",
    "ytd": -44.7,
    "is_live": true
  },
  "solum": {
    "current": 19400.0,
    "prev": 19450.0,
    "chg": -0.26,
    "currency": "KRW",
    "h52": 20750,
    "l52": 13870,
    "target": 22000,
    "rating": "強力買入",
    "ytd": -13.1,
    "is_live": true
  },
  "eink": {
    "current": 158.0,
    "prev": 155.0,
    "chg": 1.94,
    "currency": "TWD",
    "h52": 312.0,
    "l52": 164.5,
    "target": 266.83,
    "rating": "買入",
    "ytd": -41.5,
    "is_live": true
  },
  "pricer": {
    "current": 3.45,
    "prev": 3.725,
    "chg": -7.38,
    "currency": "SEK",
    "h52": 9.92,
    "l52": 2.91,
    "target": 7.13,
    "rating": "持有",
    "ytd": -65.1,
    "is_live": true
  }
}